Metadata-Version: 2.4
Name: image_processing_ar
Version: 0.0.1
Summary: Processador de imagens
Home-page: https://github.com/antonioorichard/processamento_de_imagens
Author: Antonio_Richard
Author-email: antoniorichardhc@gmail.com
Requires-Python: >=3.8
Requires-Dist: matplotlib
Requires-Dist: numpy
Requires-Dist: scikit-image>=0.16.1
Dynamic: author
Dynamic: author-email
Dynamic: description
Dynamic: description-content-type
Dynamic: home-page
Dynamic: requires-dist
Dynamic: requires-python
Dynamic: summary
